LICENSE
MANIFEST.in
NOTICE
README.md
setup.cfg
setup.py
bce_sam_cli.egg-info/PKG-INFO
bce_sam_cli.egg-info/SOURCES.txt
bce_sam_cli.egg-info/dependency_links.txt
bce_sam_cli.egg-info/entry_points.txt
bce_sam_cli.egg-info/requires.txt
bce_sam_cli.egg-info/top_level.txt
bsamcli/__init__.py
bsamcli/yamlhelper.py
bsamcli/cli/__init__.py
bsamcli/cli/command.py
bsamcli/cli/context.py
bsamcli/cli/main.py
bsamcli/cli/options.py
bsamcli/commands/__init__.py
bsamcli/commands/exceptions.py
bsamcli/commands/config/__init__.py
bsamcli/commands/deploy/__init__.py
bsamcli/commands/init/__init__.py
bsamcli/commands/layer/__init__.py
bsamcli/commands/layer/layer.py
bsamcli/commands/layer/init/__init__.py
bsamcli/commands/layer/init/cli.py
bsamcli/commands/local/__init__.py
bsamcli/commands/local/local.py
bsamcli/commands/local/cli_common/__init__.py
bsamcli/commands/local/cli_common/invoke_context.py
bsamcli/commands/local/cli_common/options.py
bsamcli/commands/local/cli_common/user_exceptions.py
bsamcli/commands/local/generate_event/__init__.py
bsamcli/commands/local/generate_event/cli.py
bsamcli/commands/local/generate_event/event_generation.py
bsamcli/commands/local/install/__init__.py
bsamcli/commands/local/install/cli.py
bsamcli/commands/local/invoke/__init__.py
bsamcli/commands/local/invoke/cli.py
bsamcli/commands/local/lib/__init__.py
bsamcli/commands/local/lib/debug_context.py
bsamcli/commands/local/lib/exceptions.py
bsamcli/commands/local/lib/local_api_service.py
bsamcli/commands/local/lib/local_lambda.py
bsamcli/commands/local/lib/local_lambda_service.py
bsamcli/commands/local/lib/provider.py
bsamcli/commands/local/lib/sam_api_provider.py
bsamcli/commands/local/lib/sam_base_provider.py
bsamcli/commands/local/lib/sam_bos_provider.py
bsamcli/commands/local/lib/sam_dueros_provider.py
bsamcli/commands/local/lib/sam_function_provider.py
bsamcli/commands/local/lib/sam_http_provider.py
bsamcli/commands/local/lib/sam_layer_provider.py
bsamcli/commands/local/lib/generated_sample_events/__init__.py
bsamcli/commands/local/lib/generated_sample_events/event-mapping.json
bsamcli/commands/local/lib/generated_sample_events/events.py
bsamcli/local/init/templates/cookiecutter-bsam-layer-python/{{cookiecutter.layer_name}}/lib/python/six-1.16.0.dist-info/INSTALLER
bsamcli/local/init/templates/cookiecutter-bsam-layer-python/{{cookiecutter.layer_name}}/lib/python/six-1.16.0.dist-info/LICENSE
bsamcli/local/init/templates/cookiecutter-bsam-layer-python/{{cookiecutter.layer_name}}/lib/python/six-1.16.0.dist-info/METADATA
bsamcli/local/init/templates/cookiecutter-bsam-layer-python/{{cookiecutter.layer_name}}/lib/python/six-1.16.0.dist-info/RECORD
bsamcli/local/init/templates/cookiecutter-bsam-layer-python/{{cookiecutter.layer_name}}/lib/python/six-1.16.0.dist-info/WHEEL
bsamcli/local/init/templates/cookiecutter-bsam-layer-python/{{cookiecutter.layer_name}}/lib/python/six-1.16.0.dist-info/top_level.txt
