Metadata-Version: 2.1
Name: bce-sam-cli
Version: 0.8.0
Summary: BCE SAM CLI is a CLI tool for local development and testing of Serverless applications
Home-page: https://github.com/bcelabs/bce-sam-cli
Author: Baidu Cloud Engine
Author-email: faas-rd@baidu.com
License: Apache License 2.0
Keywords: BCE SAM CLI
Platform: UNKNOWN
Classifier: Development Status :: 4 - Beta
Classifier: Environment :: Console
Classifier: Environment :: Other Environment
Classifier: Intended Audience :: Developers
Classifier: Intended Audience :: Information Technology
Classifier: License :: OSI Approved :: Apache Software License
Classifier: Operating System :: OS Independent
Classifier: Programming Language :: Python
Classifier: Programming Language :: Python :: 3.6
Classifier: Topic :: Internet
Classifier: Topic :: Software Development :: Build Tools
Classifier: Topic :: Utilities
Requires-Python: >=3.6
Provides-Extra: dev
License-File: LICENSE
License-File: NOTICE
